pygame_hotreload/__about__.py
pygame_hotreload/__init__.py
pygame_hotreload/crypto.py
pygame_hotreload-0.0.33.dist-info/METADATA
pygame_hotreload-0.0.33.dist-info/WHEEL
pygame_hotreload-0.0.33.dist-info/licenses/LICENSE
pygame_hotreload-0.0.33.dist-info/RECORD
