Metadata-Version: 2.4
Name: pygame-hotreload
Version: 0.0.33
Summary: A hot reload enhancer for pygame developement
Project-URL: Documentation, https://github.com/luxluth/pygame-hotreload#readme
Project-URL: Issues, https://github.com/luxluth/pygame-hotreload/issues
Project-URL: Source, https://github.com/luxluth/pygame-hotreload
Author-email: luxluth <delphin.blehoussi93@gmail.com>
License-Expression: MIT
License-File: LICENSE
Keywords: gamedev,hotreload,pygame
Classifier: Development Status :: 4 - Beta
Classifier: Programming Language :: Python
Classifier: Programming Language :: Python :: 3.9
Classifier: Programming Language :: Python :: 3.10
Classifier: Programming Language :: Python :: 3.11
Classifier: Programming Language :: Python :: Implementation :: CPython
Classifier: Programming Language :: Python :: Implementation :: PyPy
Requires-Python: >=3.10
Requires-Dist: markdown-it-py==4.0.0; python_version >= '3.10'
Requires-Dist: mdurl==0.1.2; python_version >= '3.7'
Requires-Dist: pygments==2.19.2; python_version >= '3.8'
Requires-Dist: rich==14.2.0; python_full_version >= '3.8.0'
